{
  "query": "\nSELECT externalId, connectionId, serviceId, serviceType, serviceTypeDetail, planName, status, locationAddress, supplierAccount, phoneNumber, monthlyCost\nFROM services \nWHERE supplierName = 'Telstra'\nLIMIT 15;\n",
  "command": "mysql --batch --raw --column-names --default-character-set=utf8mb4 --host gateway04.us-east-1.prod.aws.tidbcloud.com --port 4000 --user dgdAH8nVC5Tv7xw.94a9498ba7da --database SkibUwiSvPndpvTSJv52KC --execute \nSELECT externalId, connectionId, serviceId, serviceType, serviceTypeDetail, planName, status, locationAddress, supplierAccount, phoneNumber, monthlyCost\nFROM services \nWHERE supplierName = 'Telstra'\nLIMIT 15;\n",
  "rows": [
    {
      "externalId": "S0003",
      "connectionId": "",
      "serviceId": "08 8359 2256",
      "serviceType": "Internet",
      "serviceTypeDetail": "Standard Speed NBN 25Mbps/Static IP",
      "planName": "Core Internet ,Static IP",
      "status": "active",
      "locationAddress": "L 1, BG 1 6 EAST TCE, ADELAIDE SA 5000",
      "supplierAccount": "2000719405571",
      "phoneNumber": "08 8359 2256",
      "monthlyCost": "93.00"
    },
    {
      "externalId": "S0004",
      "connectionId": "",
      "serviceId": "03 5975 3104",
      "serviceType": "Internet",
      "serviceTypeDetail": "Standard Speed NBN 25Mbps/Static IP",
      "planName": "Core Internet ,Static IP",
      "status": "active",
      "locationAddress": "BG 1, G, SHOP 2, 45 MAIN ST, MORNINGTON VIC 3931",
      "supplierAccount": "2000719405571",
      "phoneNumber": "03 5975 3104",
      "monthlyCost": "93.00"
    },
    {
      "externalId": "S0005",
      "connectionId": "",
      "serviceId": "07 4725 1209",
      "serviceType": "Internet",
      "serviceTypeDetail": "Standard Speed NBN 25Mbps",
      "planName": "Core Internet",
      "status": "terminated",
      "locationAddress": "U 3, 217 - 219 INGHAM RD, WEST END QLD 4810",
      "supplierAccount": "2000719405571",
      "phoneNumber": "07 4725 1209",
      "monthlyCost": "0.00"
    },
    {
      "externalId": "S0008",
      "connectionId": "",
      "serviceId": "08 9534 1274",
      "serviceType": "Internet",
      "serviceTypeDetail": "Standard Speed NBN 25Mbps",
      "planName": "Core Internet",
      "status": "terminated",
      "locationAddress": "SHOP 2, L 602, PLAN DP62481, WEST PINJARRA WA 6208",
      "supplierAccount": "2000719405571",
      "phoneNumber": "08 9534 1274",
      "monthlyCost": "93.00"
    },
    {
      "externalId": "S0010",
      "connectionId": "",
      "serviceId": "03 5976 4649",
      "serviceType": "Internet",
      "serviceTypeDetail": "Standard Speed NBN 25Mbps/Static IP",
      "planName": "Core Internet, Static IP",
      "status": "active",
      "locationAddress": "FY 1 72 YUILLES RD, MORNINGTON VIC 3931",
      "supplierAccount": "2000719405571",
      "phoneNumber": "03 5976 4649",
      "monthlyCost": "93.00"
    },
    {
      "externalId": "S0013",
      "connectionId": "",
      "serviceId": "08 9524 2863",
      "serviceType": "Internet",
      "serviceTypeDetail": "Standard Speed NBN 25Mbps",
      "planName": "Core Internet",
      "status": "active",
      "locationAddress": "STOCKLAND BALDIVIS, BG 1, G, SHOP EX001, BALDIVIS WA 6171",
      "supplierAccount": "2000719405571",
      "phoneNumber": "08 9524 2863",
      "monthlyCost": "93.00"
    },
    {
      "externalId": "S0017",
      "connectionId": "",
      "serviceId": "07 3324 8463",
      "serviceType": "Internet",
      "serviceTypeDetail": "Standard Plus Speed NBN",
      "planName": "Unlimited Internet",
      "status": "active",
      "locationAddress": "CAMP HILL MARKETPLACE, BG 1, G, SHOP 18, CAMP HILL QLD 4152",
      "supplierAccount": "2000719405571",
      "phoneNumber": "07 3324 8463",
      "monthlyCost": "93.00"
    },
    {
      "externalId": "S0019",
      "connectionId": "",
      "serviceId": "07 4862 5254",
      "serviceType": "Internet",
      "serviceTypeDetail": "Standard Speed NBN 25Mbps",
      "planName": "Core Internet",
      "status": "active",
      "locationAddress": "SHOP 1, 37 - 43 ARANA DR, RURAL VIEW QLD 4740",
      "supplierAccount": "2000719405571",
      "phoneNumber": "07 4862 5254",
      "monthlyCost": "93.00"
    },
    {
      "externalId": "S0020",
      "connectionId": "",
      "serviceId": "SVC-0020",
      "serviceType": "Internet",
      "serviceTypeDetail": "",
      "planName": "Core Internet",
      "status": "active",
      "locationAddress": "Unknown Location",
      "supplierAccount": "2000719405571",
      "phoneNumber": "",
      "monthlyCost": "93.00"
    },
    {
      "externalId": "S0021",
      "connectionId": "",
      "serviceId": "SVC-0021",
      "serviceType": "Internet",
      "serviceTypeDetail": "",
      "planName": "Core Internet",
      "status": "active",
      "locationAddress": "Unknown Location",
      "supplierAccount": "2000719405571",
      "phoneNumber": "",
      "monthlyCost": "93.00"
    },
    {
      "externalId": "S0022",
      "connectionId": "",
      "serviceId": "SVC-0022",
      "serviceType": "Internet",
      "serviceTypeDetail": "",
      "planName": "Core Internet,Static IP",
      "status": "active",
      "locationAddress": "Unknown Location",
      "supplierAccount": "2000719405571",
      "phoneNumber": "",
      "monthlyCost": "93.00"
    },
    {
      "externalId": "S0023",
      "connectionId": "",
      "serviceId": "SVC-0023",
      "serviceType": "Internet",
      "serviceTypeDetail": "",
      "planName": "Core Internet",
      "status": "active",
      "locationAddress": "Unknown Location",
      "supplierAccount": "2000719405571",
      "phoneNumber": "",
      "monthlyCost": "93.00"
    },
    {
      "externalId": "S0024",
      "connectionId": "OAC000000469068",
      "serviceId": "OAC000000469068",
      "serviceType": "Internet",
      "serviceTypeDetail": "",
      "planName": "Upfront Internet Plan Essential",
      "status": "active",
      "locationAddress": "Unknown Location",
      "supplierAccount": "",
      "phoneNumber": "07 3891 2724",
      "monthlyCost": "109.00"
    },
    {
      "externalId": "S0025",
      "connectionId": "OAC000000406423",
      "serviceId": "OAC000000406423",
      "serviceType": "Internet",
      "serviceTypeDetail": "",
      "planName": "Upfront Internet Plan Essential",
      "status": "active",
      "locationAddress": "Unknown Location",
      "supplierAccount": "",
      "phoneNumber": "07 3846 7857",
      "monthlyCost": "109.00"
    },
    {
      "externalId": "S0026",
      "connectionId": "OAC000000455896",
      "serviceId": "OAC000000455896",
      "serviceType": "Internet",
      "serviceTypeDetail": "",
      "planName": "Upfront Internet Plan Essential",
      "status": "active",
      "locationAddress": "Unknown Location",
      "supplierAccount": "",
      "phoneNumber": "07 3863 0705",
      "monthlyCost": "109.00"
    }
  ],
  "messages": [],
  "stdout": "externalId\tconnectionId\tserviceId\tserviceType\tserviceTypeDetail\tplanName\tstatus\tlocationAddress\tsupplierAccount\tphoneNumber\tmonthlyCost\nS0003\t\t08 8359 2256\tInternet\tStandard Speed NBN 25Mbps/Static IP\tCore Internet ,Static IP\tactive\tL 1, BG 1 6 EAST TCE, ADELAIDE SA 5000\t2000719405571\t08 8359 2256\t93.00\nS0004\t\t03 5975 3104\tInternet\tStandard Speed NBN 25Mbps/Static IP\tCore Internet ,Static IP\tactive\tBG 1, G, SHOP 2, 45 MAIN ST, MORNINGTON VIC 3931\t2000719405571\t03 5975 3104\t93.00\nS0005\t\t07 4725 1209\tInternet\tStandard Speed NBN 25Mbps\tCore Internet\tterminated\tU 3, 217 - 219 INGHAM RD, WEST END QLD 4810\t2000719405571\t07 4725 1209\t0.00\nS0008\t\t08 9534 1274\tInternet\tStandard Speed NBN 25Mbps\tCore Internet\tterminated\tSHOP 2, L 602, PLAN DP62481, WEST PINJARRA WA 6208\t2000719405571\t08 9534 1274\t93.00\nS0010\t\t03 5976 4649\tInternet\tStandard Speed NBN 25Mbps/Static IP\tCore Internet, Static IP\tactive\tFY 1 72 YUILLES RD, MORNINGTON VIC 3931\t2000719405571\t03 5976 4649\t93.00\nS0013\t\t08 9524 2863\tInternet\tStandard Speed NBN 25Mbps\tCore Internet\tactive\tSTOCKLAND BALDIVIS, BG 1, G, SHOP EX001, BALDIVIS WA 6171\t2000719405571\t08 9524 2863\t93.00\nS0017\t\t07 3324 8463\tInternet\tStandard Plus Speed NBN\tUnlimited Internet\tactive\tCAMP HILL MARKETPLACE, BG 1, G, SHOP 18, CAMP HILL QLD 4152\t2000719405571\t07 3324 8463\t93.00\nS0019\t\t07 4862 5254\tInternet\tStandard Speed NBN 25Mbps\tCore Internet\tactive\tSHOP 1, 37 - 43 ARANA DR, RURAL VIEW QLD 4740\t2000719405571\t07 4862 5254\t93.00\nS0020\t\tSVC-0020\tInternet\t\tCore Internet\tactive\tUnknown Location\t2000719405571\t\t93.00\nS0021\t\tSVC-0021\tInternet\t\tCore Internet\tactive\tUnknown Location\t2000719405571\t\t93.00\nS0022\t\tSVC-0022\tInternet\t\tCore Internet,Static IP\tactive\tUnknown Location\t2000719405571\t\t93.00\nS0023\t\tSVC-0023\tInternet\t\tCore Internet\tactive\tUnknown Location\t2000719405571\t\t93.00\nS0024\tOAC000000469068\tOAC000000469068\tInternet\t\tUpfront Internet Plan Essential\tactive\tUnknown Location\t\t07 3891 2724\t109.00\nS0025\tOAC000000406423\tOAC000000406423\tInternet\t\tUpfront Internet Plan Essential\tactive\tUnknown Location\t\t07 3846 7857\t109.00\nS0026\tOAC000000455896\tOAC000000455896\tInternet\t\tUpfront Internet Plan Essential\tactive\tUnknown Location\t\t07 3863 0705\t109.00\n",
  "stderr": "",
  "execution_time_ms": 1569
}